PyCav-1.0.0a9.dist-info/DESCRIPTION.rst
PyCav-1.0.0a9.dist-info/METADATA
PyCav-1.0.0a9.dist-info/RECORD
PyCav-1.0.0a9.dist-info/WHEEL
PyCav-1.0.0a9.dist-info/metadata.json
PyCav-1.0.0a9.dist-info/top_level.txt
pycav/__init__.py
pycav/_version.py
pycav/mechanics.py
pycav/pde.py
pycav/quantum.py
